upstash_py/__init__.py
upstash_py/client.py
upstash_py/config.py
upstash_py/exception.py
upstash_py/http/decode.py
upstash_py/http/execute.py
upstash_py/play.py
upstash_py/play2.py
upstash_py/py.typed
upstash_py/schema/commands/parameters.py
upstash_py/schema/commands/returns.py
upstash_py/schema/http.py
upstash_py/schema/telemetry.py
upstash_py/utils/base.py
upstash_py/utils/comparison.py
upstash_py/utils/exception.py
upstash_py/utils/format.py
upstash_py-0.8.0.dist-info/METADATA
upstash_py-0.8.0.dist-info/WHEEL
upstash_py-0.8.0.dist-info/RECORD
